m5gfxpy.cpython-311-arm-linux-gnueabihf.so
uiflow2-0.0.4.post2.dist-info/METADATA
uiflow2-0.0.4.post2.dist-info/LICENSE
uiflow2-0.0.4.post2.dist-info/WHEEL
uiflow2-0.0.4.post2.dist-info/entry_points.txt
uiflow2-0.0.4.post2.dist-info/top_level.txt
M5/mbedtls_uiflow
M5/micropython_middle_layer.pyc
M5/startup.pyc
M5/__init__.py
M5/requests2/__init__.py
M5/hardware/pin.pyc
M5/hardware/i2c.pyc
M5/hardware/speaker.pyc
M5/hardware/uart.pyc
M5/hardware/__init__.py
M5/unit/lorawan_rui3.pyc
M5/unit/dds.pyc
M5/unit/angle.pyc
M5/unit/weight.pyc
M5/unit/flash_light.pyc
M5/unit/vmeter.pyc
M5/unit/lcd.pyc
M5/unit/key.pyc
M5/unit/kmeter.pyc
M5/unit/glass.pyc
M5/unit/midi.pyc
M5/unit/roller485.pyc
M5/unit/digi_clock.pyc
M5/unit/rfid.pyc
M5/unit/op.pyc
M5/unit/ir.pyc
M5/unit/hall_effect.pyc
M5/unit/uwb.pyc
M5/unit/adc.pyc
M5/unit/servos8.pyc
M5/unit/ac_measure.pyc
M5/unit/uhf_rfid.pyc
M5/unit/relay2.pyc
M5/unit/timerpwr.pyc
M5/unit/extio.pyc
M5/unit/glass2.pyc
M5/unit/pbhub.pyc
M5/unit/asr.pyc
M5/unit/button.pyc
M5/unit/lorawan.pyc
M5/unit/qrcode.pyc
M5/unit/relay.pyc
M5/unit/imu_pro.pyc
M5/unit/fader.pyc
M5/unit/dac2.pyc
M5/unit/co2l.pyc
M5/unit/tof4m.pyc
M5/unit/lora_e220_433.pyc
M5/unit/limit.pyc
M5/unit/nbiot.pyc
M5/unit/rs485_iso.pyc
M5/unit/thermal.pyc
M5/unit/light.pyc
M5/unit/joystick2.pyc
M5/unit/watering.pyc
M5/unit/nbiot2.pyc
M5/unit/ncir.pyc
M5/unit/extencoder.pyc
M5/unit/thermal2.pyc
M5/unit/can.pyc
M5/unit/bldc_driver.pyc
M5/unit/vibrator.pyc
M5/unit/scales.pyc
M5/unit/catm.pyc
M5/unit/gesture.pyc
M5/unit/angle8.pyc
M5/unit/laser_tx.pyc
M5/unit/grove2grove.pyc
M5/unit/tmos.pyc
M5/unit/adc_v11.pyc
M5/unit/relay4.pyc
M5/unit/mqtt.pyc
M5/unit/unit_helper.pyc
M5/unit/dac.pyc
M5/unit/id.pyc
M5/unit/encoder8.pyc
M5/unit/rollercan.pyc
M5/unit/catm_gnss.pyc
M5/unit/manifest.pyc
M5/unit/scroll.pyc
M5/unit/neco.pyc
M5/unit/rca.pyc
M5/unit/miniscale.pyc
M5/unit/hbridge.pyc
M5/unit/fan.pyc
M5/unit/extio2.pyc
M5/unit/catch.pyc
M5/unit/tvoc.pyc
M5/unit/kmeter_iso.pyc
M5/unit/bytebutton.pyc
M5/unit/envpro.pyc
M5/unit/co2.pyc
M5/unit/ameter.pyc
M5/unit/dual_button.pyc
M5/unit/rs485.pyc
uiflow2-0.0.4.post2.dist-info/RECORD
