Metadata-Version: 2.1
Name: uiflow2
Version: 0.0.4.post2
Summary: M5stack uiflow2 Python3 library.
Home-page: https://www.m5stack.com
Author: dianjixz
Author-email: dianjixz@m5stack.com
License: MIT
Classifier: Programming Language :: Python :: 3
Classifier: License :: OSI Approved :: MIT License
Classifier: Operating System :: OS Independent
Requires-Python: >=3.11
License-File: LICENSE
Requires-Dist: paho-mqtt
Requires-Dist: requests
Requires-Dist: pyserial
Requires-Dist: smbus2
Requires-Dist: evdev
Requires-Dist: pyaudio
Requires-Dist: network
Requires-Dist: typing-extensions
